{
  "frame": "1630379695.000",
  "objs": [
    {
      "obj_id": "1",
      "obj_type": "Bus",
      "psr": {
        "position": {
          "x": -7.329481464213586,
          "y": -54.96278676784732,
          "z": 0.6385898779410286
        },
        "rotation": {
          "x": 4.423858604854763e-19,
          "y": -1.8883528995062995e-18,
          "z": -1.7715091907742457
        },
        "scale": {
          "x": 10.120913080745666,
          "y": 2.7327488910563487,
          "z": 3.102245845512184
        }
      }
    },
    {
      "obj_id": "2",
      "obj_type": "Car",
      "psr": {
        "position": {
          "x": -0.9115634041318145,
          "y": 9.16461776341524,
          "z": -1.402623485326767
        },
        "rotation": {
          "x": 3.8955152565769913e-19,
          "y": -8.880569179481622e-19,
          "z": -1.3994124675684985
        },
        "scale": {
          "x": 4.345523497781707,
          "y": 2.013027045255413,
          "z": 1.469451129436493
        }
      }
    },
    {
      "obj_id": "3",
      "obj_type": "Truck",
      "psr": {
        "position": {
          "x": -14.126029333661336,
          "y": 49.416028995598936,
          "z": -1.1866825562715513
        },
        "rotation": {
          "x": -4.126646561147005e-19,
          "y": 8.775553328717033e-19,
          "z": -1.335176877775663
        },
        "scale": {
          "x": 6.825427055031859,
          "y": 2.688969173711593,
          "z": 3.343165397644043
        }
      }
    },
    {
      "obj_id": "4",
      "obj_type": "Car",
      "psr": {
        "position": {
          "x": -7.734222367303465,
          "y": 29.200362830785885,
          "z": -1.604730417728423
        },
        "rotation": {
          "x": 0,
          "y": 0,
          "z": -1.2042771838760873
        },
        "scale": {
          "x": 4.354341047020049,
          "y": 2.0876266321215042,
          "z": 1.6952840089797974
        }
      }
    },
    {
      "annotator": "i",
      "obj_attr": "static",
      "obj_id": "5",
      "obj_type": "Car",
      "psr": {
        "position": {
          "x": 3.0307941408207597,
          "y": -47.03787930855566,
          "z": -0.41942018474636655
        },
        "rotation": {
          "x": -0.00281197611463439,
          "y": 0.0017473298360278719,
          "z": 1.2852748840756965
        },
        "scale": {
          "x": 4.613175692533147,
          "y": 1.8815495886809193,
          "z": 1.5686376094818115
        }
      }
    },
    {
      "obj_attr": "static",
      "obj_id": "6",
      "obj_type": "Car",
      "psr": {
        "position": {
          "x": 5.832337632410596,
          "y": -37.74995240090356,
          "z": -0.12114040923326577
        },
        "rotation": {
          "x": -0.011082059962092015,
          "y": -0.01918201525095285,
          "z": 1.2941071881431079
        },
        "scale": {
          "x": 4.361054500695937,
          "y": 2.0124915903522593,
          "z": 1.7301356196403503
        }
      }
    },
    {
      "obj_id": "7",
      "obj_type": "Car",
      "psr": {
        "position": {
          "x": 7.626778127866197,
          "y": -31.68637556409386,
          "z": -0.4379297696202333
        },
        "rotation": {
          "x": -0.005586729790554317,
          "y": -0.0026162963086948147,
          "z": 1.2505338523223144
        },
        "scale": {
          "x": 4.550794118187447,
          "y": 1.9786825750934949,
          "z": 1.7123222351074219
        }
      }
    },
    {
      "obj_id": "8",
      "obj_type": "Car",
      "psr": {
        "position": {
          "x": 10.352021416943535,
          "y": -24.20806381024585,
          "z": -0.6902170670222737
        },
        "rotation": {
          "x": -0.004852144983601298,
          "y": -0.0018318707264297854,
          "z": 1.1807369466932618
        },
        "scale": {
          "x": 4.5,
          "y": 2.0083333333333333,
          "z": 1.5
        }
      }
    },
    {
      "obj_id": "9",
      "obj_type": "Truck",
      "psr": {
        "position": {
          "x": 12.469050771334842,
          "y": -27.517090244168354,
          "z": -0.06450058027026753
        },
        "rotation": {
          "x": -0.012552971187359062,
          "y": -0.018253413777667028,
          "z": 1.2068324460377897
        },
        "scale": {
          "x": 6.238086043451309,
          "y": 2.1966635490861064,
          "z": 2.3830922693014145
        }
      }
    },
    {
      "obj_id": "10",
      "obj_type": "Car",
      "psr": {
        "position": {
          "x": -8.825460169544545,
          "y": -42.88729679876875,
          "z": -0.36764883865001274
        },
        "rotation": {
          "x": -0.01025095951693178,
          "y": -0.022923113708974093,
          "z": -1.766277338149665
        },
        "scale": {
          "x": 4.216485486797911,
          "y": 2.0921720770977514,
          "z": 1.5341653163537445
        }
      }
    },
    {
      "obj_id": "11",
      "obj_type": "Car",
      "psr": {
        "position": {
          "x": 1.0286936245361291,
          "y": -53.78240605482222,
          "z": 0.007859733109185304
        },
        "rotation": {
          "x": 0.0038912624907156785,
          "y": -0.014597947857583211,
          "z": 1.3352008209581205
        },
        "scale": {
          "x": 4.2822378624166335,
          "y": 2.0064026091940237,
          "z": 1.7330557703971863
        }
      }
    },
    {
      "obj_attr": "static",
      "obj_id": "13",
      "obj_type": "Bus",
      "psr": {
        "position": {
          "x": 4.529556811562088,
          "y": -54.55717683232251,
          "z": 0.5118212169693681
        },
        "rotation": {
          "x": -0.009310141741887221,
          "y": -0.007278856201129114,
          "z": 1.3210364992884072
        },
        "scale": {
          "x": 10.972608620848714,
          "y": 2.9567385947956826,
          "z": 3.057128373127439
        }
      }
    },
    {
      "obj_id": "14",
      "obj_type": "Car",
      "psr": {
        "position": {
          "x": 7.324871296661873,
          "y": -43.92289148772425,
          "z": -0.1817198002108438
        },
        "rotation": {
          "x": -0.004898409300491284,
          "y": -0.013920922046780804,
          "z": 1.2882570032669616
        },
        "scale": {
          "x": 4.485782540498004,
          "y": 1.8366817136374203,
          "z": 1.6941840648651123
        }
      }
    },
    {
      "obj_id": "15",
      "obj_type": "Car",
      "psr": {
        "position": {
          "x": 9.57425810705679,
          "y": -36.37897840224568,
          "z": -0.33120954900546057
        },
        "rotation": {
          "x": -0.006892448958856701,
          "y": 0.006623887608384613,
          "z": 1.3115253974641399
        },
        "scale": {
          "x": 4.5,
          "y": 1.9462848297213622,
          "z": 1.5
        }
      }
    },
    {
      "obj_id": "16",
      "obj_type": "Car",
      "psr": {
        "position": {
          "x": -0.4801372325145789,
          "y": -59.8241313098055,
          "z": 0.14151400223657237
        },
        "rotation": {
          "x": -0.010062891863755724,
          "y": -0.019735705043672967,
          "z": 1.3639273474974585
        },
        "scale": {
          "x": 4.325487149101148,
          "y": 1.9523206314146786,
          "z": 1.6657201647758484
        }
      }
    },
    {
      "obj_id": "18",
      "obj_type": "Bus",
      "psr": {
        "position": {
          "x": -0.6583049144232973,
          "y": -74.1167111595505,
          "z": 0.8888767911391682
        },
        "rotation": {
          "x": -0.009890270453833925,
          "y": -0.019822766246867733,
          "z": 1.3464753279027617
        },
        "scale": {
          "x": 10.93738533912423,
          "y": 3.0524990900281948,
          "z": 3.1629223182876265
        }
      }
    },
    {
      "obj_id": "25",
      "obj_type": "Car",
      "psr": {
        "position": {
          "x": 33.487221242696705,
          "y": 8.111021184269703,
          "z": -0.9799170382320845
        },
        "rotation": {
          "x": -1.0266637035905735e-18,
          "y": -3.4850536660426667e-19,
          "z": 0.6544984694978735
        },
        "scale": {
          "x": 4.509065431969299,
          "y": 1.887704307103172,
          "z": 1.7807111218571663
        }
      }
    },
    {
      "obj_id": "26",
      "obj_type": "Car",
      "psr": {
        "position": {
          "x": 34.19347530607138,
          "y": 3.316334898052446,
          "z": -1.0381323368802153
        },
        "rotation": {
          "x": -0.00275115879718485,
          "y": 0.005183004234052608,
          "z": 0.8196600537579717
        },
        "scale": {
          "x": 3.959649254197272,
          "y": 1.638904955890925,
          "z": 1.6038843393325806
        }
      }
    },
    {
      "obj_id": "27",
      "obj_type": "Car",
      "psr": {
        "position": {
          "x": 36.86453316797531,
          "y": 0.7085244659227053,
          "z": -0.8412200728354092
        },
        "rotation": {
          "x": -0.0017009848041183277,
          "y": 0.005508389695722709,
          "z": 0.655595685969453
        },
        "scale": {
          "x": 3.833411796738777,
          "y": 1.7338420684443139,
          "z": 1.4276103675365448
        }
      }
    },
    {
      "obj_id": "28",
      "obj_type": "Car",
      "psr": {
        "position": {
          "x": 39.90998873911212,
          "y": 11.961734534284915,
          "z": -1.1995678735896895
        },
        "rotation": {
          "x": -0.010385180949918062,
          "y": -0.004703492161233615,
          "z": 0.6102317293237559
        },
        "scale": {
          "x": 4.120907697691855,
          "y": 1.8588045758123006,
          "z": 1.745751678943634
        }
      }
    },
    {
      "obj_id": "29",
      "obj_type": "Bus",
      "psr": {
        "position": {
          "x": 57.544060681885185,
          "y": -62.73493506947216,
          "z": 1.124420996502904
        },
        "rotation": {
          "x": 0.004471597514737193,
          "y": -0.011239591845938174,
          "z": 2.0696797304831906
        },
        "scale": {
          "x": 9.023469360324828,
          "y": 2.8266807364890494,
          "z": 3.257185357872021
        }
      }
    },
    {
      "obj_id": "30",
      "obj_type": "Bus",
      "psr": {
        "position": {
          "x": 62.24980149483148,
          "y": -76.66435767764801,
          "z": 1.5982030630111694
        },
        "rotation": {
          "x": 0,
          "y": 0,
          "z": 2.032716584468939
        },
        "scale": {
          "x": 10.590452014600693,
          "y": 2.7331379021041324,
          "z": 3.0821616649627686
        }
      }
    },
    {
      "obj_id": "31",
      "obj_type": "Car",
      "psr": {
        "position": {
          "x": 40.45081226542171,
          "y": 7.619066526938035,
          "z": -0.9569251034325142
        },
        "rotation": {
          "x": 0.010445542429323421,
          "y": -0.0013858410766399683,
          "z": 0.712611755489863
        },
        "scale": {
          "x": 4.263030608744195,
          "y": 1.767676675876913,
          "z": 1.5073047876358032
        }
      }
    },
    {
      "obj_id": "35",
      "obj_type": "Truck",
      "psr": {
        "position": {
          "x": 46.72577458252311,
          "y": 27.699761322971366,
          "z": -0.9765394843903373
        },
        "rotation": {
          "x": 0.005706666131874321,
          "y": 0.0008183190139642607,
          "z": -1.07228729330466
        },
        "scale": {
          "x": 4.682877200944132,
          "y": 2.0026328044999353,
          "z": 2.5349078476428986
        }
      }
    },
    {
      "obj_attr": "umbrella",
      "obj_id": "43",
      "obj_type": "Pedestrian",
      "psr": {
        "position": {
          "x": -9.632561668457733,
          "y": -17.34652590354132,
          "z": -0.3021477976403053
        },
        "rotation": {
          "x": 0.0024883762864346933,
          "y": -0.0073883227665018664,
          "z": 1.3816156351394548
        },
        "scale": {
          "x": 0.9941834588454745,
          "y": 0.9947373990957169,
          "z": 1.7496344447135925
        }
      }
    }
  ],
  "scene": "scene-000080"
}