{
  "frame": "1630376275.500",
  "objs": [
    {
      "obj_id": "1",
      "obj_type": "Car",
      "psr": {
        "position": {
          "x": -1.8141093075504036,
          "y": -55.20735456128002,
          "z": -0.30895768105983734
        },
        "rotation": {
          "x": 3.867755891639943e-18,
          "y": 1.1493742304285367e-18,
          "z": -1.4922565104551522
        },
        "scale": {
          "x": 4.058527599032187,
          "y": 2.0426071642316415,
          "z": 1.6831534802913666
        }
      }
    },
    {
      "obj_id": "2",
      "obj_type": "Car",
      "psr": {
        "position": {
          "x": 2.180627843701027,
          "y": -38.048037526883974,
          "z": -0.5407511554658271
        },
        "rotation": {
          "x": 8.932565616915772e-18,
          "y": 5.828941028004335e-18,
          "z": -1.5446163880149812
        },
        "scale": {
          "x": 4.191451924624294,
          "y": 2.03720670442349,
          "z": 1.7489753849804401
        }
      }
    },
    {
      "obj_id": "3",
      "obj_type": "Car",
      "psr": {
        "position": {
          "x": 1.879394630352222,
          "y": -81.19758219923891,
          "z": 0.20711591839790344
        },
        "rotation": {
          "x": 0,
          "y": 0,
          "z": -1.7069932794306546
        },
        "scale": {
          "x": 4.410345802905138,
          "y": 2.0568759614607246,
          "z": 1.446869134902954
        }
      }
    },
    {
      "obj_id": "4",
      "obj_type": "Car",
      "psr": {
        "position": {
          "x": -8.162289714632537,
          "y": -3.4946690432396297,
          "z": -0.9425173439085484
        },
        "rotation": {
          "x": 0,
          "y": 0,
          "z": -1.5446163880149815
        },
        "scale": {
          "x": 4.813360518382784,
          "y": 1.9883367524725095,
          "z": 1.9669528231024742
        }
      }
    },
    {
      "obj_id": "5",
      "obj_type": "Car",
      "psr": {
        "position": {
          "x": -9.859730577923422,
          "y": 23.39307759878623,
          "z": -1.328566513604784
        },
        "rotation": {
          "x": 0,
          "y": 0,
          "z": -1.507256510455152
        },
        "scale": {
          "x": 4.388546228742623,
          "y": 2.1814394606970025,
          "z": 1.394274755610752
        }
      }
    },
    {
      "obj_id": "6",
      "obj_type": "Truck",
      "psr": {
        "position": {
          "x": -11.318749755776228,
          "y": 47.67706631185925,
          "z": -0.5769759900867939
        },
        "rotation": {
          "x": 0,
          "y": 0,
          "z": -1.5333430342749537
        },
        "scale": {
          "x": 6.1248709069324185,
          "y": 2.3807690575828726,
          "z": 2.980222225189209
        }
      }
    },
    {
      "obj_id": "7",
      "obj_type": "Car",
      "psr": {
        "position": {
          "x": -10.579744620212018,
          "y": 76.72386755271457,
          "z": -1.7959401845932006
        },
        "rotation": {
          "x": 0,
          "y": 0,
          "z": -1.5969762655748116
        },
        "scale": {
          "x": 3.7215037693296926,
          "y": 2.008233424777022,
          "z": 1.4719061851501465
        }
      }
    },
    {
      "obj_id": "8",
      "obj_type": "Car",
      "psr": {
        "position": {
          "x": -13.166993023521954,
          "y": 80.2161639960085,
          "z": -1.9365820296456802
        },
        "rotation": {
          "x": -0.022250629854301925,
          "y": 0.013630447031294192,
          "z": -1.5318479129114209
        },
        "scale": {
          "x": 4.5,
          "y": 2.0784741097847594,
          "z": 1.835304168970032
        }
      }
    }
  ],
  "scene": "scene-000040"
}