{
  "frame": "1630376274.000",
  "objs": [
    {
      "obj_id": "1",
      "obj_type": "Car",
      "psr": {
        "position": {
          "x": -2.242783141833599,
          "y": -51.408293410601686,
          "z": -0.0791234225034714
        },
        "rotation": {
          "x": 1.1942310900527662e-18,
          "y": -1.1039358644873934e-18,
          "z": -1.4922565104551522
        },
        "scale": {
          "x": 4.058527599032187,
          "y": 2.0426071642316415,
          "z": 1.6831534802913666
        }
      }
    },
    {
      "obj_id": "2",
      "obj_type": "Car",
      "psr": {
        "position": {
          "x": 2.4987922455291365,
          "y": -30.757537963047067,
          "z": -0.5399994812906073
        },
        "rotation": {
          "x": 4.804066671375056e-18,
          "y": -4.9315123824254054e-18,
          "z": -1.5969762655748123
        },
        "scale": {
          "x": 4.191451924624294,
          "y": 2.03720670442349,
          "z": 1.7489753849804401
        }
      }
    },
    {
      "obj_id": "3",
      "obj_type": "Car",
      "psr": {
        "position": {
          "x": 2.039230344042725,
          "y": -71.74686483864187,
          "z": 0.2934150695800781
        },
        "rotation": {
          "x": 0,
          "y": 0,
          "z": -1.6511378545733741
        },
        "scale": {
          "x": 4.410345802905138,
          "y": 2.0568759614607246,
          "z": 1.446869134902954
        }
      }
    },
    {
      "obj_id": "4",
      "obj_type": "Car",
      "psr": {
        "position": {
          "x": -9.121522725576726,
          "y": -5.7517870544404595,
          "z": -0.8632912747561932
        },
        "rotation": {
          "x": 0,
          "y": 0,
          "z": -1.4922565104551522
        },
        "scale": {
          "x": 4.813360518382784,
          "y": 1.9883367524725095,
          "z": 1.9669528231024742
        }
      }
    },
    {
      "obj_id": "5",
      "obj_type": "Car",
      "psr": {
        "position": {
          "x": -11.188803929699345,
          "y": 20.315364641758226,
          "z": -1.3182542324066162
        },
        "rotation": {
          "x": 0,
          "y": 0,
          "z": -1.4922565104551522
        },
        "scale": {
          "x": 4.388546228742623,
          "y": 2.1814394606970025,
          "z": 1.5074634552001953
        }
      }
    },
    {
      "obj_id": "6",
      "obj_type": "Truck",
      "psr": {
        "position": {
          "x": -12.783196764787476,
          "y": 43.25556938203272,
          "z": -0.9480666145914682
        },
        "rotation": {
          "x": 0.0002776946380118537,
          "y": -0.0002944406421052758,
          "z": -1.4996472798722968
        },
        "scale": {
          "x": 6.1248709069324185,
          "y": 2.3807690575828726,
          "z": 2.980222225189209
        }
      }
    },
    {
      "obj_id": "7",
      "obj_type": "Car",
      "psr": {
        "position": {
          "x": -11.561439592217345,
          "y": 60.710130961786454,
          "z": -2.4074854850769043
        },
        "rotation": {
          "x": 0,
          "y": 0,
          "z": -1.5969762655748116
        },
        "scale": {
          "x": 3.7215037693296926,
          "y": 2.008233424777022,
          "z": 1.4719061851501465
        }
      }
    },
    {
      "obj_id": "8",
      "obj_type": "Car",
      "psr": {
        "position": {
          "x": -14.509164050105202,
          "y": 69.12373491159619,
          "z": -2.7396679005475204
        },
        "rotation": {
          "x": -0.030692427181027025,
          "y": 0.01459949674918936,
          "z": -1.5191713957591955
        },
        "scale": {
          "x": 4.5,
          "y": 2.0784741097847594,
          "z": 1.835304168970032
        }
      }
    }
  ],
  "scene": "scene-000040"
}