{
  "version": "2.1.0",
  "flags": {},
  "shapes": [
    {
      "label": "person",
      "text": "",
      "points": [
        [
          363.37030029296875,
          401.68505859375
        ],
        [
          385.96820068359375,
          463.940185546875
        ]
      ],
      "group_id": null,
      "shape_type": "rectangle",
      "flags": {},
      "attributes": {}
    },
    {
      "label": "car",
      "text": "",
      "points": [
        [
          840.6329956054688,
          423.9886474609375
        ],
        [
          947.1619262695312,
          525.727294921875
        ]
      ],
      "group_id": null,
      "shape_type": "rectangle",
      "flags": {},
      "attributes": {}
    },
    {
      "label": "car",
      "text": "",
      "points": [
        [
          3.3216552734375,
          586.871337890625
        ],
        [
          1103.3731689453125,
          713.611328125
        ]
      ],
      "group_id": null,
      "shape_type": "rectangle",
      "flags": {},
      "attributes": {}
    },
    {
      "label": "car",
      "text": "",
      "points": [
        [
          634.8206787109375,
          416.9666748046875
        ],
        [
          812.2037353515625,
          487.9793701171875
        ]
      ],
      "group_id": null,
      "shape_type": "rectangle",
      "flags": {},
      "attributes": {}
    },
    {
      "label": "car",
      "text": "",
      "points": [
        [
          670.72998046875,
          442.9244384765625
        ],
        [
          778.47900390625,
          507.8624267578125
        ]
      ],
      "group_id": null,
      "shape_type": "rectangle",
      "flags": {},
      "attributes": {}
    },
    {
      "label": "car",
      "text": "",
      "points": [
        [
          525.5833740234375,
          433.63470458984375
        ],
        [
          546.9991455078125,
          450.99505615234375
        ]
      ],
      "group_id": null,
      "shape_type": "rectangle",
      "flags": {},
      "attributes": {}
    }
  ],
  "imagePath": "..\\sustech_night_4k60fps\\frame_89.jpg",
  "imageData": null,
  "imageHeight": 720,
  "imageWidth": 1280
}