{
  "version": "2.1.0",
  "flags": {},
  "shapes": [
    {
      "label": "car",
      "text": "",
      "points": [
        [
          0.797698974609375,
          221.50808715820312
        ],
        [
          294.4792785644531,
          546.772216796875
        ]
      ],
      "group_id": null,
      "shape_type": "rectangle",
      "flags": {},
      "attributes": {}
    }
  ],
  "imagePath": "..\\sustech_night_4k60fps\\frame_3.jpg",
  "imageData": null,
  "imageHeight": 720,
  "imageWidth": 1280
}